{
  "format_version": "1.10.0",
  "minecraft:client_entity": {
    "description": {
      "identifier": "minecraft:skeleton",
      "min_engine_version": "1.8.0",
      "materials": {
        "default": "skeleton",
        "hp": "entity_emissive_alpha"
      },
      "geometry": {
        "default": "geometry.skeleton.v1.8",
        "hp": "geometry.health_bar"
      },
      "spawn_egg": {
        "texture": "spawn_egg",
        "texture_index": 9
      },
      "animations": {
        "look_at_target_default": "animation.humanoid.look_at_target.default",
        "look_at_target_gliding": "animation.humanoid.look_at_target.gliding",
        "look_at_target_swimming": "animation.humanoid.look_at_target.swimming",
        "move": "animation.humanoid.move",
        "riding.arms": "animation.humanoid.riding.arms",
        "riding.legs": "animation.humanoid.riding.legs",
        "holding": "animation.humanoid.holding",
        "brandish_spear": "animation.humanoid.brandish_spear",
        "charging": "animation.humanoid.charging",
        "attack.rotations": "animation.humanoid.attack.rotations",
        "sneaking": "animation.humanoid.sneaking",
        "bob": "animation.humanoid.bob",
        "damage_nearby_mobs": "animation.humanoid.damage_nearby_mobs",
        "bow_and_arrow": "animation.humanoid.bow_and_arrow",
        "swimming": "animation.zombie.swimming",
        "use_item_progress": "animation.humanoid.use_item_progress",
        "skeleton_attack": "animation.skeleton.attack",
        "look_at_target": "controller.animation.humanoid.look_at_target",
        "move1": "controller.animation.humanoid.move",
        "riding": "controller.animation.humanoid.riding",
        "holding1": "controller.animation.humanoid.holding",
        "brandish_spear1": "controller.animation.humanoid.brandish_spear",
        "charging1": "controller.animation.humanoid.charging",
        "attack": "controller.animation.humanoid.attack",
        "sneaking1": "controller.animation.humanoid.sneaking",
        "bob1": "controller.animation.humanoid.bob",
        "damage_nearby_mobs1": "controller.animation.humanoid.damage_nearby_mobs",
        "bow_and_arrow1": "controller.animation.humanoid.bow_and_arrow",
        "swimming1": "controller.animation.zombie.swimming",
        "use_item_progress1": "controller.animation.humanoid.use_item_progress",
        "skeleton_attack1": "controller.animation.skeleton.attack",

        "hp": "animation.health_humanoid"
      },
      "render_controllers": [
        "controller.render.skeleton",
        "controller.render.hp"
      ],
      "enable_attachables": true,
      "scripts": {
        "pre_animation": [
          "variable.health = math.round(query.health / query.max_health * 100);",
          "variable.tcos0 = (Math.cos(query.modified_distance_moved * 38.17) * query.modified_move_speed / variable.gliding_speed_value) * 57.3;"
        ],
        "animate": [
          "look_at_target",
          "move1",
          "riding", 
          "holding1",
          "brandish_spear1",
          "charging1",
          "attack",
          "sneaking1",
          "bob1",
          "damage_nearby_mobs1",
          "bow_and_arrow1",
          "use_item_progress1",
          "skeleton_attack1",
          "swimming1",
"hp"
        ],
        "variables": {
          "variable.hp": "public"
        },
        "initialize": [
          "variable.hp = query.health;"
        ]
      },

      "textures": {
        "default": "textures/entity/skeleton/skeleton",
        "hp100": "textures/hp/hp100",
        "hp99": "textures/hp/hp99",
        "hp98": "textures/hp/hp98",
        "hp97": "textures/hp/hp97",
        "hp96": "textures/hp/hp96",
        "hp95": "textures/hp/hp95",
        "hp94": "textures/hp/hp94",
        "hp93": "textures/hp/hp93",
        "hp92": "textures/hp/hp92",
        "hp91": "textures/hp/hp91",
        "hp90": "textures/hp/hp90",
        "hp89": "textures/hp/hp89",
        "hp88": "textures/hp/hp88",
        "hp87": "textures/hp/hp87",
        "hp86": "textures/hp/hp86",
        "hp85": "textures/hp/hp85",
        "hp84": "textures/hp/hp84",
        "hp83": "textures/hp/hp83",
        "hp82": "textures/hp/hp82",
        "hp81": "textures/hp/hp81",
        "hp80": "textures/hp/hp80",
        "hp79": "textures/hp/hp79",
        "hp78": "textures/hp/hp78",
        "hp77": "textures/hp/hp77",
        "hp76": "textures/hp/hp76",
        "hp75": "textures/hp/hp75",
        "hp74": "textures/hp/hp74",
        "hp73": "textures/hp/hp73",
        "hp72": "textures/hp/hp72",
        "hp71": "textures/hp/hp71",
        "hp70": "textures/hp/hp70",
        "hp69": "textures/hp/hp69",
        "hp68": "textures/hp/hp68",
        "hp67": "textures/hp/hp67",
        "hp66": "textures/hp/hp66",
        "hp65": "textures/hp/hp65",
        "hp64": "textures/hp/hp64",
        "hp63": "textures/hp/hp63",
        "hp62": "textures/hp/hp62",
        "hp61": "textures/hp/hp61",
        "hp60": "textures/hp/hp60",
        "hp59": "textures/hp/hp59",
        "hp58": "textures/hp/hp58",
        "hp57": "textures/hp/hp57",
        "hp56": "textures/hp/hp56",
        "hp55": "textures/hp/hp55",
        "hp54": "textures/hp/hp54",
        "hp53": "textures/hp/hp53",
        "hp52": "textures/hp/hp52",
        "hp51": "textures/hp/hp51",
        "hp50": "textures/hp/hp50",
        "hp49": "textures/hp/hp49",
        "hp48": "textures/hp/hp48",
        "hp47": "textures/hp/hp47",
        "hp46": "textures/hp/hp46",
        "hp45": "textures/hp/hp45",
        "hp44": "textures/hp/hp44",
        "hp43": "textures/hp/hp43",
        "hp42": "textures/hp/hp42",
        "hp41": "textures/hp/hp41",
        "hp40": "textures/hp/hp40",
        "hp39": "textures/hp/hp39",
        "hp38": "textures/hp/hp38",
        "hp37": "textures/hp/hp37",
        "hp36": "textures/hp/hp36",
        "hp35": "textures/hp/hp35",
        "hp34": "textures/hp/hp34",
        "hp33": "textures/hp/hp33",
        "hp32": "textures/hp/hp32",
        "hp31": "textures/hp/hp31",
        "hp30": "textures/hp/hp30",
        "hp29": "textures/hp/hp29",
        "hp28": "textures/hp/hp28",
        "hp27": "textures/hp/hp27",
        "hp26": "textures/hp/hp26",
        "hp25": "textures/hp/hp25",
        "hp24": "textures/hp/hp24",
        "hp23": "textures/hp/hp23",
        "hp22": "textures/hp/hp22",
        "hp21": "textures/hp/hp21",
        "hp20": "textures/hp/hp20",
        "hp19": "textures/hp/hp19",
        "hp18": "textures/hp/hp18",
        "hp17": "textures/hp/hp17",
        "hp16": "textures/hp/hp16",
        "hp15": "textures/hp/hp15",
        "hp14": "textures/hp/hp14",
        "hp13": "textures/hp/hp13",
        "hp12": "textures/hp/hp12",
        "hp11": "textures/hp/hp11",
        "hp10": "textures/hp/hp10",
        "hp9": "textures/hp/hp9",
        "hp8": "textures/hp/hp8",
        "hp7": "textures/hp/hp7",
        "hp6": "textures/hp/hp6",
        "hp5": "textures/hp/hp5",
        "hp4": "textures/hp/hp4",
        "hp3": "textures/hp/hp3",
        "hp2": "textures/hp/hp2",
        "hp1": "textures/hp/hp1",
        "hp0": "textures/hp/hp1"
      }
    }
  }
}